{"nodes": [{"id": "d_documents_github_nutriscan_app_components_header_tsx", "label": "header.tsx", "file_type": "code", "source_file": "D:\\Documents\\Github\\nutriscan\\app\\components\\header.tsx", "source_location": "L1"}, {"id": "components_header_nav_links", "label": "NAV_LINKS", "file_type": "code", "source_file": "D:\\Documents\\Github\\nutriscan\\app\\components\\header.tsx", "source_location": "L10"}, {"id": "components_header_header", "label": "Header()", "file_type": "code", "source_file": "D:\\Documents\\Github\\nutriscan\\app\\components\\header.tsx", "source_location": "L16"}], "edges": [{"source": "d_documents_github_nutriscan_app_components_header_tsx", "target": "react", "relation": "imports_from", "context": "import", "confidence": "EXTRACTED", "source_file": "D:\\Documents\\Github\\nutriscan\\app\\components\\header.tsx", "source_location": "L3", "weight": 1.0}, {"source": "d_documents_github_nutriscan_app_components_header_tsx", "target": "link", "relation": "imports_from", "context": "import", "confidence": "EXTRACTED", "source_file": "D:\\Documents\\Github\\nutriscan\\app\\components\\header.tsx", "source_location": "L4", "weight": 1.0}, {"source": "d_documents_github_nutriscan_app_components_header_tsx", "target": "next_themes", "relation": "imports_from", "context": "import", "confidence": "EXTRACTED", "source_file": "D:\\Documents\\Github\\nutriscan\\app\\components\\header.tsx", "source_location": "L5", "weight": 1.0}, {"source": "d_documents_github_nutriscan_app_components_header_tsx", "target": "lucide_react", "relation": "imports_from", "context": "import", "confidence": "EXTRACTED", "source_file": "D:\\Documents\\Github\\nutriscan\\app\\components\\header.tsx", "source_location": "L6", "weight": 1.0}, {"source": "d_documents_github_nutriscan_app_components_header_tsx", "target": "image", "relation": "imports_from", "context": "import", "confidence": "EXTRACTED", "source_file": "D:\\Documents\\Github\\nutriscan\\app\\components\\header.tsx", "source_location": "L7", "weight": 1.0}, {"source": "d_documents_github_nutriscan_app_components_header_tsx", "target": "d_documents_github_nutriscan_lib_utils_ts", "relation": "imports_from", "context": "import", "confidence": "EXTRACTED", "source_file": "D:\\Documents\\Github\\nutriscan\\app\\components\\header.tsx", "source_location": "L8", "weight": 1.0}, {"source": "d_documents_github_nutriscan_app_components_header_tsx", "target": "lib_utils_cn", "relation": "imports", "context": "import", "confidence": "EXTRACTED", "source_file": "D:\\Documents\\Github\\nutriscan\\app\\components\\header.tsx", "source_location": "L8", "weight": 1.0}, {"source": "d_documents_github_nutriscan_app_components_header_tsx", "target": "components_header_nav_links", "relation": "contains", "confidence": "EXTRACTED", "source_file": "D:\\Documents\\Github\\nutriscan\\app\\components\\header.tsx", "source_location": "L10", "weight": 1.0}, {"source": "d_documents_github_nutriscan_app_components_header_tsx", "target": "components_header_header", "relation": "contains", "confidence": "EXTRACTED", "source_file": "D:\\Documents\\Github\\nutriscan\\app\\components\\header.tsx", "source_location": "L16", "weight": 1.0}], "raw_calls": [{"caller_nid": "components_header_header", "callee": "useState", "is_member_call": false, "source_file": "D:\\Documents\\Github\\nutriscan\\app\\components\\header.tsx", "source_location": "L17"}, {"caller_nid": "components_header_header", "callee": "useState", "is_member_call": false, "source_file": "D:\\Documents\\Github\\nutriscan\\app\\components\\header.tsx", "source_location": "L18"}, {"caller_nid": "components_header_header", "callee": "useState", "is_member_call": false, "source_file": "D:\\Documents\\Github\\nutriscan\\app\\components\\header.tsx", "source_location": "L19"}, {"caller_nid": "components_header_header", "callee": "useTheme", "is_member_call": false, "source_file": "D:\\Documents\\Github\\nutriscan\\app\\components\\header.tsx", "source_location": "L20"}, {"caller_nid": "components_header_header", "callee": "useEffect", "is_member_call": false, "source_file": "D:\\Documents\\Github\\nutriscan\\app\\components\\header.tsx", "source_location": "L22"}, {"caller_nid": "components_header_header", "callee": "cn", "is_member_call": false, "source_file": "D:\\Documents\\Github\\nutriscan\\app\\components\\header.tsx", "source_location": "L33"}, {"caller_nid": "components_header_header", "callee": "map", "is_member_call": true, "source_file": "D:\\Documents\\Github\\nutriscan\\app\\components\\header.tsx", "source_location": "L65"}, {"caller_nid": "components_header_header", "callee": "cn", "is_member_call": false, "source_file": "D:\\Documents\\Github\\nutriscan\\app\\components\\header.tsx", "source_location": "L111"}, {"caller_nid": "components_header_header", "callee": "map", "is_member_call": true, "source_file": "D:\\Documents\\Github\\nutriscan\\app\\components\\header.tsx", "source_location": "L117"}]}