{"nodes": [{"id": "d_documents_github_nutriscan_app_components_landing_trustbadges_tsx", "label": "TrustBadges.tsx", "file_type": "code", "source_file": "D:\\Documents\\Github\\nutriscan\\app\\components\\landing\\TrustBadges.tsx", "source_location": "L1"}, {"id": "landing_trustbadges_stats", "label": "stats", "file_type": "code", "source_file": "D:\\Documents\\Github\\nutriscan\\app\\components\\landing\\TrustBadges.tsx", "source_location": "L3"}, {"id": "landing_trustbadges_trustbadges", "label": "TrustBadges()", "file_type": "code", "source_file": "D:\\Documents\\Github\\nutriscan\\app\\components\\landing\\TrustBadges.tsx", "source_location": "L26"}], "edges": [{"source": "d_documents_github_nutriscan_app_components_landing_trustbadges_tsx", "target": "lucide_react", "relation": "imports_from", "context": "import", "confidence": "EXTRACTED", "source_file": "D:\\Documents\\Github\\nutriscan\\app\\components\\landing\\TrustBadges.tsx", "source_location": "L1", "weight": 1.0}, {"source": "d_documents_github_nutriscan_app_components_landing_trustbadges_tsx", "target": "landing_trustbadges_stats", "relation": "contains", "confidence": "EXTRACTED", "source_file": "D:\\Documents\\Github\\nutriscan\\app\\components\\landing\\TrustBadges.tsx", "source_location": "L3", "weight": 1.0}, {"source": "d_documents_github_nutriscan_app_components_landing_trustbadges_tsx", "target": "landing_trustbadges_trustbadges", "relation": "contains", "confidence": "EXTRACTED", "source_file": "D:\\Documents\\Github\\nutriscan\\app\\components\\landing\\TrustBadges.tsx", "source_location": "L26", "weight": 1.0}], "raw_calls": [{"caller_nid": "landing_trustbadges_trustbadges", "callee": "map", "is_member_call": true, "source_file": "D:\\Documents\\Github\\nutriscan\\app\\components\\landing\\TrustBadges.tsx", "source_location": "L31"}]}